.clang-format
.flake8
.gitignore
.gitmodules
CHANGELOG.md
CODEOWNERS
CODE_OF_CONDUCT
Dockerfile
Dockerfile-cuda
Dockerfile-embedded
LICENSE
MANIFEST.in
Makefile
README.md
__init__.py
description.txt
packages.txt
setup.py
./src/opendr/__init__.py
./src/opendr/_setup.py
./src/opendr/_version.py
./src/opendr/control/__init__.py
./src/opendr/engine/__init__.py
./src/opendr/engine/constants.py
./src/opendr/engine/data.py
./src/opendr/engine/datasets.py
./src/opendr/engine/example_learner.py
./src/opendr/engine/learners.py
./src/opendr/engine/target.py
./src/opendr/perception/__init__.py
./src/opendr/perception/gesture_recognition/__init__.py
./src/opendr/perception/gesture_recognition/dependencies.ini
./src/opendr/perception/gesture_recognition/gesture_recognition_learner.py
./src/opendr/perception/gesture_recognition/algorithm/__init__.py
./src/opendr/perception/gesture_recognition/algorithm/config/__init__.py
./src/opendr/perception/gesture_recognition/algorithm/config/nanodet_plus_m_1.5x_416.yml
./src/opendr/perception/gesture_recognition/algorithm/data/__init__.py
./src/opendr/perception/gesture_recognition/algorithm/data/dataset/__init__.py
./src/opendr/perception/gesture_recognition/algorithm/data/dataset/hagrid2coco.py
./src/opendr/planning/__init__.py
./src/opendr/simulation/__init__.py
./src/opendr/utils/__init__.py
./src/opendr_toolkit_gesture_recognition.egg-info/PKG-INFO
./src/opendr_toolkit_gesture_recognition.egg-info/SOURCES.txt
./src/opendr_toolkit_gesture_recognition.egg-info/dependency_links.txt
./src/opendr_toolkit_gesture_recognition.egg-info/requires.txt
./src/opendr_toolkit_gesture_recognition.egg-info/top_level.txt
src/opendr/_setup.py
src/opendr/_version.py
src/opendr/perception/gesture_recognition/__init__.py
src/opendr/perception/gesture_recognition/dependencies.ini
src/opendr/perception/gesture_recognition/gesture_recognition_learner.py
src/opendr/perception/gesture_recognition/algorithm/__init__.py
src/opendr/perception/gesture_recognition/algorithm/config/__init__.py
src/opendr/perception/gesture_recognition/algorithm/config/nanodet_plus_m_1.5x_416.yml
src/opendr/perception/gesture_recognition/algorithm/data/__init__.py
src/opendr/perception/gesture_recognition/algorithm/data/dataset/__init__.py
